{
	"name": "dataflow1",
	"properties": {
		"type": "MappingDataFlow",
		"typeProperties": {
			"sources": [
				{
					"linkedService": {
						"referenceName": "TeamDesk1",
						"type": "LinkedServiceReference"
					},
					"name": "source1"
				}
			],
			"sinks": [
				{
					"dataset": {
						"referenceName": "Json1",
						"type": "DatasetReference"
					},
					"name": "sink1"
				}
			],
			"transformations": [],
			"scriptLines": [
				"source(allowSchemaDrift: true,",
				"     validateSchema: false,",
				"     store: 'teamdesk',",
				"     format: 'rest',",
				"     table: 't_933707',",
				"     view: 'v_7668056') ~> source1",
				"source1 sink(allowSchemaDrift: true,",
				"     validateSchema: false,",
				"     input(",
				"          name as string",
				"     ),",
				"     skipDuplicateMapInputs: true,",
				"     skipDuplicateMapOutputs: true) ~> sink1"
			]
		}
	}
}